{
  "age": {
    "20代": {"VIBE": 1, "WILD": 1},
    "30代": {"PURE": 1, "BOLD": 1},
    "40代": {"CALM": 1, "BOLD": 1},
    "50代以上": {"CALM": 1, "PURE": 1}
  },
  "gender": {
    "女性っぽい": {"SOUL": 1, "PURE": 1},
    "男性っぽい": {"BOLD": 1, "CALM": 1},
    "どちらでもない気分": {"VIBE": 1}
  },
  "likes": {
    "チーズ": {"BOLD": 1, "CALM": 1},
    "オリーブ": {"PURE": 1, "SOUL": 1},
    "肉料理": {"BOLD": 1},
    "魚介料理": {"PURE": 1, "SOUL": 1},
    "スイーツ": {"SOUL": 1},
    "コーヒー": {"CALM": 1},
    "紅茶": {"PURE": 1},
    "ビール": {"VIBE": 1},
    "カクテル": {"VIBE": 1, "WILD": 1}
  }
}
